{
  "kind": "youtube#video",
  "etag": "rJC2DpBUkzIohn8Susa8VxjU4b4",
  "id": "KzNbrrBCmdE",
  "snippet": {
    "publishedAt": "2024-09-19T11:05:27Z",
    "channelId": "UCkYqhFNmhCzkefHsHS652hw",
    "title": "Compromises you need to think about for your #azuredevops migration. Excerpt 2",
    "description": "Compromises you need to think about for your #azuredevops migration. Excerpt 2. Watch the full video at https://www.youtube.com/@nakedAgility #agile #devops #devopsmigration Visit https://www.nkdagility.com if you need help with your migration.",
    "thumbnails": {
      "default": {
        "url": "https://i.ytimg.com/vi/KzNbrrBCmdE/default.jpg",
        "width": 120,
        "height": 90
      },
      "medium": {
        "url": "https://i.ytimg.com/vi/KzNbrrBCmdE/mqdefault.jpg",
        "width": 320,
        "height": 180
      },
      "high": {
        "url": "https://i.ytimg.com/vi/KzNbrrBCmdE/hqdefault.jpg",
        "width": 480,
        "height": 360
      },
      "standard": {
        "url": "https://i.ytimg.com/vi/KzNbrrBCmdE/sddefault.jpg",
        "width": 640,
        "height": 480
      },
      "maxres": {
        "url": "https://i.ytimg.com/vi/KzNbrrBCmdE/maxresdefault.jpg",
        "width": 1280,
        "height": 720
      }
    },
    "channelTitle": "naked Agility with Martin Hinshelwood",
    "tags": [
      "Azure DevOps migration",
      "Azure Devops",
      "DevOps",
      "DevOps migration",
      "Microsoft\\"
    ],
    "categoryId": "28",
    "liveBroadcastContent": "none",
    "localized": {
      "title": "Compromises you need to think about for your #azuredevops migration. Excerpt 2",
      "description": "Compromises you need to think about for your #azuredevops migration. Excerpt 2. Watch the full video at https://www.youtube.com/@nakedAgility #agile #devops #devopsmigration Visit https://www.nkdagility.com if you need help with your migration."
    }
  },
  "contentDetails": {
    "duration": "PT52S",
    "dimension": "2d",
    "definition": "hd",
    "caption": "false",
    "licensedContent": false,
    "contentRating": {},
    "projection": "rectangular"
  }
}
