{
  "kind": "youtube#video",
  "etag": "aXOon6ApW_p8j3HoqvzEquM66uc",
  "id": "iCDEX6oHy7A",
  "snippet": {
    "publishedAt": "2020-04-07T20:33:45Z",
    "channelId": "UCkYqhFNmhCzkefHsHS652hw",
    "title": "Ep 004: Chat with Jim Sammons on professionalism and conflicting priorities",
    "description": "Jim is a Professional Scrum Trainer and an active Agile consultant at Loop Agility. We will be chatting about professionalism and conflicting priorities at 20:00 on the 7th April 2020\n\nGuest Jim Sammons: https://www.scrum.org/jim-sammons\n\nMartin Hinshelwood: https://nkdagility.com/company/about-martin-hinshelwood/",
    "thumbnails": {
      "default": {
        "url": "https://i.ytimg.com/vi/iCDEX6oHy7A/default.jpg",
        "width": 120,
        "height": 90
      },
      "medium": {
        "url": "https://i.ytimg.com/vi/iCDEX6oHy7A/mqdefault.jpg",
        "width": 320,
        "height": 180
      },
      "high": {
        "url": "https://i.ytimg.com/vi/iCDEX6oHy7A/hqdefault.jpg",
        "width": 480,
        "height": 360
      },
      "standard": {
        "url": "https://i.ytimg.com/vi/iCDEX6oHy7A/sddefault.jpg",
        "width": 640,
        "height": 480
      },
      "maxres": {
        "url": "https://i.ytimg.com/vi/iCDEX6oHy7A/maxresdefault.jpg",
        "width": 1280,
        "height": 720
      }
    },
    "channelTitle": "naked Agility with Martin Hinshelwood",
    "tags": [
      "Scrum",
      "Agility",
      "Professional",
      "Product Owner",
      "Scrum Team"
    ],
    "categoryId": "28",
    "liveBroadcastContent": "none",
    "localized": {
      "title": "Ep 004: Chat with Jim Sammons on professionalism and conflicting priorities",
      "description": "Jim is a Professional Scrum Trainer and an active Agile consultant at Loop Agility. We will be chatting about professionalism and conflicting priorities at 20:00 on the 7th April 2020\n\nGuest Jim Sammons: https://www.scrum.org/jim-sammons\n\nMartin Hinshelwood: https://nkdagility.com/company/about-martin-hinshelwood/"
    },
    "defaultAudioLanguage": "en-GB"
  },
  "contentDetails": {
    "duration": "PT1H24M31S",
    "dimension": "2d",
    "definition": "hd",
    "caption": "false",
    "licensedContent": false,
    "contentRating": {},
    "projection": "rectangular"
  }
}
