{
  "related": [
    {
      "Title": "How Does Your Consulting Experience Manifest in the Training Environment?",
      "Slug": "how-does-your-consulting-experience-manifest-in-the-training-environment",
      "Reference": "resources/videos/youtube/AwkxZ9RS_0g",
      "EntryId": "AwkxZ9RS_0g",
      "EntryKind": "resource",
      "EntryType": "videos",
      "EntryGenAt": "2025-05-29T20:41:23.4284015Z",
      "Similarity": 0.7832032613252656
    },
    {
      "Title": "Why Are a Scrum Team Better Served by an Agile Consultant than a Professional Coach?",
      "Slug": "why-are-a-scrum-team-better-served-by-an-agile-consultant-than-a-professional-coach",
      "Reference": "resources/videos/youtube/LkphLIbmjkI",
      "EntryId": "LkphLIbmjkI",
      "EntryKind": "resource",
      "EntryType": "videos",
      "EntryGenAt": "2025-05-29T20:41:18.2262647Z",
      "Similarity": 0.7706296281341078
    },
    {
      "Title": "Agile Coach Versus Professional Coach",
      "Slug": "agile-coach-versus-professional-coach",
      "Reference": "resources/videos/youtube/I5YoOAai-m4",
      "EntryId": "I5YoOAai-m4",
      "EntryKind": "resource",
      "EntryType": "videos",
      "EntryGenAt": "2025-05-29T20:41:17.3426866Z",
      "Similarity": 0.7619222100157198
    },
    {
      "Title": "Why do you prefer agile consulting over agile coaching?",
      "Slug": "why-do-you-prefer-agile-consulting-over-agile-coaching",
      "Reference": "resources/videos/youtube/FJjiCodxyK4",
      "EntryId": "FJjiCodxyK4",
      "EntryKind": "resource",
      "EntryType": "videos",
      "EntryGenAt": "2025-05-29T20:43:15.2162Z",
      "Similarity": 0.7612455229574819
    },
    {
      "Title": "Unlocking Agile Consulting: Transform Your Organisation with Diverse Strategies and Continuous Learning",
      "Slug": "unlocking-agile-consulting-transform-your-organisation-with-diverse-strategies-and-continuous-learning",
      "Reference": "resources/videos/youtube/82_yTGt9pLM",
      "EntryId": "82_yTGt9pLM",
      "EntryKind": "resource",
      "EntryType": "videos",
      "EntryGenAt": "2025-05-29T20:41:29.9730961Z",
      "Similarity": 0.760803445637531
    },
    {
      "Title": "The Evolution of Agile Learning: Insights from Scrum.org's Webinar",
      "Slug": "the-evolution-of-agile-learning-insights-from-scrum-org's-webinar",
      "Reference": "resources/blog/2023/2023-12-14-the-evolution-of-agile-learning-insights-from-scrum-orgs-webinar",
      "EntryId": "Ax5c4JFICyO",
      "EntryKind": "resource",
      "EntryType": "blog",
      "EntryGenAt": "2025-05-29T20:37:52.225472Z",
      "Similarity": 0.6042331511776594
    },
    {
      "Title": "There is no \"do agile\" there is only \"be agile\"",
      "Slug": "there-is-no-do-agile-there-is-only-be-agile",
      "Reference": "resources/blog/2013/2013-09-01-there-is-no-do-agile-there-is-only-be-agile",
      "EntryId": "QIFsyx_OqLG",
      "EntryKind": "resource",
      "EntryType": "blog",
      "EntryGenAt": "2025-05-29T20:47:40.8066486Z",
      "Similarity": 0.5918484347088098
    },
    {
      "Title": "Professional Scrum is for everyone in your organisation",
      "Slug": "professional-scrum-is-for-everyone-in-your-organisation",
      "Reference": "resources/blog/2018/2018-01-16-professional-scrum-everyone-organisation",
      "EntryId": "Cr7wjIJ8Uvb",
      "EntryKind": "resource",
      "EntryType": "blog",
      "EntryGenAt": "2025-05-29T20:45:30.4173121Z",
      "Similarity": 0.5879292789593493
    },
    {
      "Title": "Agile Is Not Easier Than Traditional Methods: Common Misconceptions",
      "Slug": "agile-is-not-easier-than-traditional-methods-common-misconceptions",
      "Reference": "resources/signals/2025-03-08-agile-is-not-easier-than-traditional-methods-common-misconceptions",
      "EntryId": "ZGwpGOoHHBQ",
      "EntryKind": "resource",
      "EntryType": "signals",
      "EntryGenAt": "2025-05-29T20:32:00.9117677Z",
      "Similarity": 0.5868722156035119
    },
    {
      "Title": "My journey into Professional Scrum",
      "Slug": "journey-professional-scrum",
      "Reference": "resources/blog/2015/2015-02-04-journey-professional-scrum",
      "EntryId": "PqEhZ1JIcDe",
      "EntryKind": "resource",
      "EntryType": "blog",
      "EntryGenAt": "2025-05-29T20:46:09.2967685Z",
      "Similarity": 0.5828344553534092
    },
    {
      "Title": "From Unused Gym Memberships to Agile Implementation The Parallels of Misapplied Investments",
      "Slug": "from-unused-gym-memberships-to-agile-implementation-the-parallels-of-misapplied-investments",
      "Reference": "resources/blog/2023/2023-08-03-from-unused-gym-memberships-to-agile-implementation-the-parallels-of-misapplied-investments",
      "EntryId": "mzVDd2JFtHO",
      "EntryKind": "resource",
      "EntryType": "blog",
      "EntryGenAt": "2025-05-29T20:40:39.9009778Z",
      "Similarity": 0.5759319025113201
    },
    {
      "Title": "Companies often say \"we-are going Agile!\" as if declaring it makes it so",
      "Slug": "companies-often-say-we-are-going-agile-as-if-declaring-it-makes-it-so",
      "Reference": "resources/signals/2025-04-25-companies-often-say-we-are-going-agile-as-if-declaring-it-makes-it-so",
      "EntryId": "otmDMgDEp-i",
      "EntryKind": "resource",
      "EntryType": "signals",
      "EntryGenAt": "2025-05-29T20:31:10.7263951Z",
      "Similarity": 0.5677487994405449
    },
    {
      "Title": "Hiring a Scrum Master is hard",
      "Slug": "hiring-a-scrum-master-is-hard",
      "Reference": "resources/signals/2025-02-16-hiring-a-scrum-master-is-hard",
      "EntryId": "CHfV0DI2Plv",
      "EntryKind": "resource",
      "EntryType": "signals",
      "EntryGenAt": "2025-05-29T20:32:36.8186218Z",
      "Similarity": 0.5647766510423646
    },
    {
      "Title": "Agile and Scrum are often misunderstood",
      "Slug": "agile-and-scrum-are-often-misunderstood",
      "Reference": "resources/signals/2025-05-04-agile-and-scrum-are-often-misunderstood",
      "EntryId": "Oi_yiyEHZbM",
      "EntryKind": "resource",
      "EntryType": "signals",
      "EntryGenAt": "2025-05-29T20:30:58.0652061Z",
      "Similarity": 0.5517597433705291
    },
    {
      "Title": "Key Skills Scrum Masters Need: Technical, Business, Organisational",
      "Slug": "key-skills-scrum-masters-need-technical-business-organisational",
      "Reference": "resources/signals/2025-02-18-key-skills-scrum-masters-need-technical-business-organisational",
      "EntryId": "KVrBKTQ-Yc-",
      "EntryKind": "resource",
      "EntryType": "signals",
      "EntryGenAt": "2025-05-29T20:32:32.2187416Z",
      "Similarity": 0.5515731511458651
    },
    {
      "Title": "Investing for Business Agility - Using evidence-based portfolio management to achieve better business outcomes",
      "Slug": "investing-for-business-agility-using-evidence-based-portfolio-management-to-achieve-better-business-outcomes",
      "Reference": "resources/guides/evidence-based-portfolio-management",
      "EntryId": "KD08D48Weks",
      "EntryKind": "resource",
      "EntryType": "guides",
      "EntryGenAt": "2025-05-29T20:34:03.8865036Z",
      "Similarity": 0.5341783175829348
    },
    {
      "Title": "Detecting Agile BS",
      "Slug": "detecting-agile-bs",
      "Reference": "resources/guides/detecting-agile-bs",
      "EntryId": "Tt8SPr3xJER",
      "EntryKind": "resource",
      "EntryType": "guides",
      "EntryGenAt": "2025-05-29T20:34:22.2965514Z",
      "Similarity": 0.4832394025425872
    },
    {
      "Title": "Manifesto for Agile Software Development",
      "Slug": "manifesto-for-agile-software-development",
      "Reference": "resources/guides/manifesto-for-agile-software-development",
      "EntryId": "poyC7fUGitC",
      "EntryKind": "resource",
      "EntryType": "guides",
      "EntryGenAt": "2025-05-29T20:34:13.6054486Z",
      "Similarity": 0.4614850588272958
    },
    {
      "Title": "The Scrum Guide",
      "Slug": "the-scrum-guide",
      "Reference": "resources/guides/scrum-guide",
      "EntryId": "59gcHh1fYtC",
      "EntryKind": "resource",
      "EntryType": "guides",
      "EntryGenAt": "2025-05-29T20:34:07.6058577Z",
      "Similarity": 0.43629878506593156
    },
    {
      "Title": "Kanban Guide for Scrum Teams",
      "Slug": "kanban-guide-for-scrum-teams",
      "Reference": "resources/guides/kanban-guide-for-scrum-teams",
      "EntryId": "Z3HzXH_nmmz",
      "EntryKind": "resource",
      "EntryType": "guides",
      "EntryGenAt": "2025-05-29T20:34:04.8234949Z",
      "Similarity": 0.4348881624676117
    }
  ]
}
