{
  "related": [
    {
      "Title": "Are there any Scrum courses that teach you how to scale Scrum?",
      "Slug": "are-there-any-scrum-courses-that-teach-you-how-to-scale-scrum",
      "Reference": "resources/videos/youtube/vubnDXYXiL0",
      "EntryId": "vubnDXYXiL0",
      "EntryKind": "resource",
      "EntryType": "videos",
      "EntryGenAt": "2025-05-29T20:39:11.1911048Z",
      "Similarity": 0.8307158939922205
    },
    {
      "Title": "Mastering the Art of Scaling Agile: Strategies to Maintain Agility Across Multiple Teams",
      "Slug": "mastering-the-art-of-scaling-agile-strategies-to-maintain-agility-across-multiple-teams",
      "Reference": "resources/videos/youtube/8lUeIYEGg7k",
      "EntryId": "8lUeIYEGg7k",
      "EntryKind": "resource",
      "EntryType": "videos",
      "EntryGenAt": "2025-05-29T20:32:16.7113552Z",
      "Similarity": 0.7832758097597713
    },
    {
      "Title": "Transform Your Scrum Master Journey: Key Insights from the Advanced PSM Course",
      "Slug": "transform-your-scrum-master-journey-key-insights-from-the-advanced-psm-course",
      "Reference": "resources/videos/youtube/QGXlCm_B5zA",
      "EntryId": "QGXlCm_B5zA",
      "EntryKind": "resource",
      "EntryType": "videos",
      "EntryGenAt": "2025-05-29T20:43:26.6146913Z",
      "Similarity": 0.7829433513820965
    },
    {
      "Title": "Unlocking Success: How the Professional Scrum Product Owner Course Transforms Your Agile Journey",
      "Slug": "unlocking-success-how-the-professional-scrum-product-owner-course-transforms-your-agile-journey",
      "Reference": "resources/videos/youtube/6SSgETsq8IQ",
      "EntryId": "6SSgETsq8IQ",
      "EntryKind": "resource",
      "EntryType": "videos",
      "EntryGenAt": "2025-05-29T20:44:12.8063115Z",
      "Similarity": 0.7779946708865669
    },
    {
      "Title": "What are 3 key takeaways for a scrum team after attending an APS immersive learning experience course?",
      "Slug": "what-are-3-key-takeaways-for-a-scrum-team-after-attending-an-aps-immersive-learning-experience-course",
      "Reference": "resources/videos/youtube/221BbTUqw7Q",
      "EntryId": "221BbTUqw7Q",
      "EntryKind": "resource",
      "EntryType": "videos",
      "EntryGenAt": "2025-05-29T20:40:27.0925993Z",
      "Similarity": 0.7768797566720951
    },
    {
      "Title": "Scaled Professional Scrum with Nexus (SPS) with Certification",
      "Slug": "scaled-professional-scrum-with-nexus-sps-with-certification",
      "Reference": "capabilities/training-courses/scrumorg-scaled-professional-scrum-with-nexus",
      "EntryId": "scaled-professional-scrum-with-nexus-sps-with-certification",
      "EntryKind": "program",
      "EntryType": "course",
      "EntryGenAt": "2025-07-23T06:16:51.0925532Z",
      "Similarity": 0.7322892608249337
    },
    {
      "Title": "My journey into Professional Scrum",
      "Slug": "journey-professional-scrum",
      "Reference": "resources/blog/2015/2015-02-04-journey-professional-scrum",
      "EntryId": "PqEhZ1JIcDe",
      "EntryKind": "resource",
      "EntryType": "blog",
      "EntryGenAt": "2025-05-29T20:46:09.2967685Z",
      "Similarity": 0.7240729883196364
    },
    {
      "Title": "Scaling Professional Scrum with Visual Studio Team Services",
      "Slug": "scaling-professional-scrum-with-visual-studio-team-services",
      "Reference": "resources/blog/2016/2016-07-06-scaling-professional-scrum-visual-studio-team-services",
      "EntryId": "pErrcS8DxcQ",
      "EntryKind": "resource",
      "EntryType": "blog",
      "EntryGenAt": "2025-05-29T20:45:49.4945797Z",
      "Similarity": 0.7108529396090915
    },
    {
      "Title": "Big Scrum: All you need and not enough",
      "Slug": "big-scrum-all-you-need-and-not-enough",
      "Reference": "resources/blog/2015/2015-07-01-big-scrum-all-you-need-and-not-enough",
      "EntryId": "yCJ5ERuJHUU",
      "EntryKind": "resource",
      "EntryType": "blog",
      "EntryGenAt": "2025-05-29T20:45:59.0928039Z",
      "Similarity": 0.702760214498038
    },
    {
      "Title": "Upcomming Scrum at Scale Workshop from Scrum.org",
      "Slug": "announcing-scrum-at-scale-workshop-scrum-org",
      "Reference": "resources/blog/2014/2014-10-22-announcing-scrum-at-scale-workshop-scrum-org",
      "EntryId": "eSPePG8uDaZ",
      "EntryKind": "resource",
      "EntryType": "blog",
      "EntryGenAt": "2025-05-29T20:46:30.7916751Z",
      "Similarity": 0.6998915457546626
    },
    {
      "Title": "Maximising Value from Applying Professional Scrum Training",
      "Slug": "maximising-value-from-applying-professional-scrum-training",
      "Reference": "resources/signals/2025-06-09-maximising-value-from-applying-professional-scrum-training",
      "EntryId": "Db-LocFYG0R",
      "EntryKind": "resource",
      "EntryType": "signals",
      "EntryGenAt": "2025-06-17T16:57:59.839719Z",
      "Similarity": 0.6914954721110024
    },
    {
      "Title": "Professional Scrum Foundations in Alameda, California",
      "Slug": "professional-scrum-foundations-in-alameda-california",
      "Reference": "resources/blog/2012/2012-10-26-professional-scrum-foundations-in-alameda-california",
      "EntryId": "If3c0gr1udB",
      "EntryKind": "resource",
      "EntryType": "blog",
      "EntryGenAt": "2025-05-29T20:48:58.1730368Z",
      "Similarity": 0.6897008566028033
    },
    {
      "Title": "Applying Professional Scrum (APS) Course with Certification",
      "Slug": "applying-professional-scrum-aps-with-certification",
      "Reference": "capabilities/training-courses/scrumorg-applying-professional-scrum",
      "EntryId": "applying-professional-scrum-aps-with-certification",
      "EntryKind": "program",
      "EntryType": "course",
      "EntryGenAt": "2025-07-23T06:16:50.2672911Z",
      "Similarity": 0.6748598209313575
    },
    {
      "Title": "Professional Scrum Product Owner (PSPO) Course with Certification",
      "Slug": "professional-scrum-product-owner-pspo-with-certification",
      "Reference": "capabilities/training-courses/scrumorg-professional-scrum-product-owner",
      "EntryId": "professional-scrum-product-owner-pspo-with-certification",
      "EntryKind": "program",
      "EntryType": "course",
      "EntryGenAt": "2025-07-23T06:16:42.4811201Z",
      "Similarity": 0.6577425465758626
    },
    {
      "Title": "David thought he already knew Scrum",
      "Slug": "david-thought-he-already-knew-scrum",
      "Reference": "resources/signals/2025-05-26-david-thought-he-already-knew-scrum",
      "EntryId": "qpdjJhtaABE",
      "EntryKind": "resource",
      "EntryType": "signals",
      "EntryGenAt": "2025-05-29T20:30:27.3967646Z",
      "Similarity": 0.6407408227187035
    },
    {
      "Title": "Nexus Guide",
      "Slug": "nexus-guide",
      "Reference": "resources/guides/nexus-framework",
      "EntryId": "iC8MlA3TE7S",
      "EntryKind": "resource",
      "EntryType": "guides",
      "EntryGenAt": "2025-05-29T20:34:05.7118225Z",
      "Similarity": 0.6403589192902155
    },
    {
      "Title": "Professional Scrum Master (PSM) Course with Certification",
      "Slug": "professional-scrum-master-psm-with-certification",
      "Reference": "capabilities/training-courses/scrumorg-professional-scrum-master",
      "EntryId": "professional-scrum-master-psm-with-certification",
      "EntryKind": "program",
      "EntryType": "course",
      "EntryGenAt": "2025-07-23T06:16:49.4894406Z",
      "Similarity": 0.6310524178307017
    },
    {
      "Title": "When you scale Scrum, the challenge isn’t just delivery—it coherence",
      "Slug": "when-you-scale-scrum-the-challenge-isn-t-just-delivery-it-coherence",
      "Reference": "resources/signals/2025-05-27-when-you-scale-scrum-the-challenge-isn-t-just-delivery-it-coherence",
      "EntryId": "eGzb1hJRtoc",
      "EntryKind": "resource",
      "EntryType": "signals",
      "EntryGenAt": "2025-05-29T20:30:26.2489948Z",
      "Similarity": 0.6288397485888833
    },
    {
      "Title": "A two-day Scrum Master certification doesn’t make you a Scrum Master",
      "Slug": "a-two-day-scrum-master-certification-doesn-t-make-you-a-scrum-master",
      "Reference": "resources/signals/2025-02-27-a-two-day-scrum-master-certification-doesn-t-make-you-a-scrum-master",
      "EntryId": "aYJLiPejAHG",
      "EntryKind": "resource",
      "EntryType": "signals",
      "EntryGenAt": "2025-05-29T20:32:13.0217205Z",
      "Similarity": 0.623559748989409
    },
    {
      "Title": "Hiring a Scrum Master is hard",
      "Slug": "hiring-a-scrum-master-is-hard",
      "Reference": "resources/signals/2025-02-16-hiring-a-scrum-master-is-hard",
      "EntryId": "CHfV0DI2Plv",
      "EntryKind": "resource",
      "EntryType": "signals",
      "EntryGenAt": "2025-05-29T20:32:36.8186218Z",
      "Similarity": 0.6082016466389787
    },
    {
      "Title": "Applying Scaled Portfolio Kanban",
      "Slug": "applying-scaled-portfolio-kanban",
      "Reference": "capabilities/training-courses/prokanban-applying-scaled-portfolio-kanban",
      "EntryId": "applying-scaled-portfolio-kanban",
      "EntryKind": "program",
      "EntryType": "course",
      "EntryGenAt": "2025-07-23T06:16:29.7835152Z",
      "Similarity": 0.5990002450860877
    },
    {
      "Title": "The Scrum Guide",
      "Slug": "the-scrum-guide",
      "Reference": "resources/guides/scrum-guide",
      "EntryId": "59gcHh1fYtC",
      "EntryKind": "resource",
      "EntryType": "guides",
      "EntryGenAt": "2025-05-29T20:34:07.6058577Z",
      "Similarity": 0.5800959850877097
    },
    {
      "Title": "Kanban Guide for Scrum Teams",
      "Slug": "kanban-guide-for-scrum-teams",
      "Reference": "resources/guides/kanban-guide-for-scrum-teams",
      "EntryId": "Z3HzXH_nmmz",
      "EntryKind": "resource",
      "EntryType": "guides",
      "EntryGenAt": "2025-05-29T20:34:04.8234949Z",
      "Similarity": 0.5685373434260776
    },
    {
      "Title": "Investing for Business Agility - Using evidence-based portfolio management to achieve better business outcomes",
      "Slug": "investing-for-business-agility-using-evidence-based-portfolio-management-to-achieve-better-business-outcomes",
      "Reference": "resources/guides/evidence-based-portfolio-management",
      "EntryId": "KD08D48Weks",
      "EntryKind": "resource",
      "EntryType": "guides",
      "EntryGenAt": "2025-05-29T20:34:03.8865036Z",
      "Similarity": 0.5677105812307889
    },
    {
      "Title": "Detecting Agile BS",
      "Slug": "detecting-agile-bs",
      "Reference": "resources/guides/detecting-agile-bs",
      "EntryId": "Tt8SPr3xJER",
      "EntryKind": "resource",
      "EntryType": "guides",
      "EntryGenAt": "2025-05-29T20:34:22.2965514Z",
      "Similarity": 0.49704940126199093
    }
  ]
}
