{
  "kind": "youtube#video",
  "etag": "rad3bLzSy_gDrnDivOe2XrGLarI",
  "id": "h6yumCOP-aE",
  "snippet": {
    "publishedAt": "2024-03-01T07:00:17Z",
    "channelId": "UCkYqhFNmhCzkefHsHS652hw",
    "title": "3 best ways to wreck your Kanban adoption.  Not having a working agreement.",
    "description": "Crafting Success: The Power of Team Agreements in Kanban\n\nThe Foundation of Effective Collaboration\n\nThe cornerstone of any successful Kanban or agile strategy is not the methodology itself but the team's agreement on how to work together. Without a shared understanding and explicit agreement, teams can easily fall into disarray, with each member pulling in different directions based on individual preferences rather than a unified strategy.\n\nThe Pitfalls of Assumed Agreement\n\nLack of Direction: Without a clear, agreed-upon approach, team members may select tasks based on personal interest rather than strategic value, leading to a lack of cohesion and direction.\nMisconception of Frameworks: Merely adopting Scrum or any other framework without a detailed working agreement does not guarantee alignment. These frameworks provide structure, not solutions.\nThe Danger of Vanity Metrics: Relying on superficial metrics like story points or planning poker without a consensus on their use and value can lead to misguided efforts and ineffective measurement of progress.\nBuilding a Winning Strategy\nExplicit Working Agreements: Sit down as a team to decide on your approach, tools, and methods. This agreement forms the basis of your collaborative efforts and ensures everyone is aligned towards common goals.\nDefine Success: Clearly outline what success looks like for your team and how it aligns with the organization's objectives. This includes defining small wins that contribute to larger goals.\nCustomize Your Approach: Whether you're implementing Kanban, Scrum, or a hybrid strategy, the key is to adapt the methodology to fit your team's unique needs and agree on the best practices that will guide your work.\n\nCollaboration Over Dictation\n\nJoint Decision-Making: Imposing methods and tools top-down without team buy-in is a recipe for resistance and inefficiency. Collaboration and consensus-building lead to a more cohesive and motivated team.\nIterative Improvement: Your working agreement is not set in stone. Regularly review and adjust your strategies based on feedback and changing circumstances to continuously refine your workflow.\n\nCall to Action\n\nAligning on how to work together is not just a step towards improving your Kanban or agile practices; it's a leap towards building a more cohesive, efficient, and motivated team. If you're navigating the complexities of implementing a Kanban strategy or seeking to enhance your team's collaboration, we're here to offer guidance, support, and expert advice. Don't let disarray hold you back. Click the link below to learn more and get in touch today for personalized support tailored to your team's needs. Together, we can build a framework for success that resonates with every member of your team.",
    "thumbnails": {
      "default": {
        "url": "https://i.ytimg.com/vi/h6yumCOP-aE/default.jpg",
        "width": 120,
        "height": 90
      },
      "medium": {
        "url": "https://i.ytimg.com/vi/h6yumCOP-aE/mqdefault.jpg",
        "width": 320,
        "height": 180
      },
      "high": {
        "url": "https://i.ytimg.com/vi/h6yumCOP-aE/hqdefault.jpg",
        "width": 480,
        "height": 360
      },
      "standard": {
        "url": "https://i.ytimg.com/vi/h6yumCOP-aE/sddefault.jpg",
        "width": 640,
        "height": 480
      },
      "maxres": {
        "url": "https://i.ytimg.com/vi/h6yumCOP-aE/maxresdefault.jpg",
        "width": 1280,
        "height": 720
      }
    },
    "channelTitle": "naked Agility with Martin Hinshelwood",
    "tags": [
      "Working agreements",
      "Kanban",
      "Kanban approach",
      "Kanban method",
      "Kanban training",
      "Kanban coaching",
      "Kanban consultant"
    ],
    "categoryId": "28",
    "liveBroadcastContent": "none",
    "localized": {
      "title": "3 best ways to wreck your Kanban adoption.  Not having a working agreement.",
      "description": "Crafting Success: The Power of Team Agreements in Kanban\n\nThe Foundation of Effective Collaboration\n\nThe cornerstone of any successful Kanban or agile strategy is not the methodology itself but the team's agreement on how to work together. Without a shared understanding and explicit agreement, teams can easily fall into disarray, with each member pulling in different directions based on individual preferences rather than a unified strategy.\n\nThe Pitfalls of Assumed Agreement\n\nLack of Direction: Without a clear, agreed-upon approach, team members may select tasks based on personal interest rather than strategic value, leading to a lack of cohesion and direction.\nMisconception of Frameworks: Merely adopting Scrum or any other framework without a detailed working agreement does not guarantee alignment. These frameworks provide structure, not solutions.\nThe Danger of Vanity Metrics: Relying on superficial metrics like story points or planning poker without a consensus on their use and value can lead to misguided efforts and ineffective measurement of progress.\nBuilding a Winning Strategy\nExplicit Working Agreements: Sit down as a team to decide on your approach, tools, and methods. This agreement forms the basis of your collaborative efforts and ensures everyone is aligned towards common goals.\nDefine Success: Clearly outline what success looks like for your team and how it aligns with the organization's objectives. This includes defining small wins that contribute to larger goals.\nCustomize Your Approach: Whether you're implementing Kanban, Scrum, or a hybrid strategy, the key is to adapt the methodology to fit your team's unique needs and agree on the best practices that will guide your work.\n\nCollaboration Over Dictation\n\nJoint Decision-Making: Imposing methods and tools top-down without team buy-in is a recipe for resistance and inefficiency. Collaboration and consensus-building lead to a more cohesive and motivated team.\nIterative Improvement: Your working agreement is not set in stone. Regularly review and adjust your strategies based on feedback and changing circumstances to continuously refine your workflow.\n\nCall to Action\n\nAligning on how to work together is not just a step towards improving your Kanban or agile practices; it's a leap towards building a more cohesive, efficient, and motivated team. If you're navigating the complexities of implementing a Kanban strategy or seeking to enhance your team's collaboration, we're here to offer guidance, support, and expert advice. Don't let disarray hold you back. Click the link below to learn more and get in touch today for personalized support tailored to your team's needs. Together, we can build a framework for success that resonates with every member of your team."
    },
    "defaultAudioLanguage": "en-GB"
  },
  "contentDetails": {
    "duration": "PT5M2S",
    "dimension": "2d",
    "definition": "hd",
    "caption": "false",
    "licensedContent": false,
    "contentRating": {},
    "projection": "rectangular"
  }
}
