{
  "related": [
    {
      "Title": "The Power of Technical Excellence in Agile Development",
      "Slug": "the-power-of-technical-excellence-in-agile-development",
      "Reference": "resources/videos/youtube/JTYCRehkN5U",
      "EntryId": "JTYCRehkN5U",
      "EntryKind": "resource",
      "EntryType": "videos",
      "EntryGenAt": "2025-05-29T20:36:18.1675748Z",
      "Similarity": 0.7222678955104501
    },
    {
      "Title": "Cultivating a Culture of Engineering Excellence: The Essential Role of Technical Leadership",
      "Slug": "cultivating-a-culture-of-engineering-excellence-the-essential-role-of-technical-leadership",
      "Reference": "resources/videos/youtube/CXOrndz5lN4",
      "EntryId": "CXOrndz5lN4",
      "EntryKind": "resource",
      "EntryType": "videos",
      "EntryGenAt": "2025-05-29T20:33:30.4248028Z",
      "Similarity": 0.7076012363340001
    },
    {
      "Title": "Transforming Engineering Excellence: The Power of Naked Agility in Quality and Leadership",
      "Slug": "transforming-engineering-excellence-the-power-of-naked-agility-in-quality-and-leadership",
      "Reference": "resources/videos/youtube/tdOSrPOlyAI",
      "EntryId": "tdOSrPOlyAI",
      "EntryKind": "resource",
      "EntryType": "videos",
      "EntryGenAt": "2025-05-29T20:33:26.49665Z",
      "Similarity": 0.6844835134228126
    },
    {
      "Title": "Great Scrum Masters Need Technical, Business, and Organisational Mastery",
      "Slug": "great-scrum-masters-need-technical-business-and-organisational-mastery",
      "Reference": "resources/blog/2025/2025-03-12-great-scrum-masters-need-technical-business-and-organisational-mastery",
      "EntryId": "dQjKsWR5qfn",
      "EntryKind": "resource",
      "EntryType": "blog",
      "EntryGenAt": "2025-05-29T20:31:44.494158Z",
      "Similarity": 0.6702003805395326
    },
    {
      "Title": "Mastering Technical Debt: Strategies to Transform Challenges into Opportunities for Your Development Team",
      "Slug": "mastering-technical-debt-strategies-to-transform-challenges-into-opportunities-for-your-development-team",
      "Reference": "resources/videos/youtube/PZa77csy5r8",
      "EntryId": "PZa77csy5r8",
      "EntryKind": "resource",
      "EntryType": "videos",
      "EntryGenAt": "2025-05-29T20:33:28.6511547Z",
      "Similarity": 0.6691065634311913
    },
    {
      "Title": "Mastering Agility: Balancing Engineering Excellence and Effective Processes in a Rapidly Changing Business Landscape",
      "Slug": "mastering-agility-balancing-engineering-excellence-and-effective-processes-in-a-rapidly-changing-business-landscape",
      "Reference": "resources/videos/youtube/i_DglXgaePM",
      "EntryId": "i_DglXgaePM",
      "EntryKind": "resource",
      "EntryType": "videos",
      "EntryGenAt": "2025-05-29T20:45:13.2366201Z",
      "Similarity": 0.6611785221571369
    },
    {
      "Title": "Engineering Excellence",
      "Slug": "engineering-excellence",
      "Reference": "outcomes/engineering-excellence",
      "EntryId": "HHVaKkQviFN",
      "EntryKind": "marketing",
      "EntryType": "outcomes",
      "EntryGenAt": "2025-10-31T18:45:05.1908969Z",
      "Similarity": 0.6611476769279614
    },
    {
      "Title": "Why Scrum Masters Need Technical Expertise to Guide Teams",
      "Slug": "why-scrum-masters-need-technical-expertise-to-guide-teams",
      "Reference": "resources/signals/2025-03-28-why-scrum-masters-need-technical-expertise-to-guide-teams",
      "EntryId": "_0eaUkX1o1q",
      "EntryKind": "resource",
      "EntryType": "signals",
      "EntryGenAt": "2025-05-29T20:31:39.4740027Z",
      "Similarity": 0.6465897786567153
    },
    {
      "Title": "Too many Scrum Masters believe they don’t need technical skills",
      "Slug": "too-many-scrum-masters-believe-they-don-t-need-technical-skills",
      "Reference": "resources/signals/2025-03-24-too-many-scrum-masters-believe-they-don-t-need-technical-skills",
      "EntryId": "q_OupO_abR_",
      "EntryKind": "resource",
      "EntryType": "signals",
      "EntryGenAt": "2025-05-29T20:31:42.9229143Z",
      "Similarity": 0.6404164282695654
    },
    {
      "Title": "Technical Leadership",
      "Slug": "technical-leadership",
      "Reference": "outcomes/technical-leadership",
      "EntryId": "wJMDXD_JAJt",
      "EntryKind": "marketing",
      "EntryType": "outcomes",
      "EntryGenAt": "2025-10-31T18:44:57.1558144Z",
      "Similarity": 0.6291698921692214
    },
    {
      "Title": "Are technical skills required to be a Scrum Master?",
      "Slug": "are-technical-skills-required-to-be-a-scrum-master",
      "Reference": "resources/blog/2019/2019-09-01-are-technical-skills-required-to-be-a-scrum-master",
      "EntryId": "foi9MYyc1vq",
      "EntryKind": "resource",
      "EntryType": "blog",
      "EntryGenAt": "2025-05-29T20:45:24.6946034Z",
      "Similarity": 0.6268074624799141
    },
    {
      "Title": "Key Skills Scrum Masters Need: Technical, Business, Organisational",
      "Slug": "key-skills-scrum-masters-need-technical-business-organisational",
      "Reference": "resources/signals/2025-02-18-key-skills-scrum-masters-need-technical-business-organisational",
      "EntryId": "KVrBKTQ-Yc-",
      "EntryKind": "resource",
      "EntryType": "signals",
      "EntryGenAt": "2025-05-29T20:32:32.2187416Z",
      "Similarity": 0.6217047388461031
    },
    {
      "Title": "Scrum Masters are not glorified meeting schedulers",
      "Slug": "scrum-masters-are-not-glorified-meeting-schedulers",
      "Reference": "resources/signals/2025-03-09-scrum-masters-are-not-glorified-meeting-schedulers",
      "EntryId": "ASC0IjY5nKr",
      "EntryKind": "resource",
      "EntryType": "signals",
      "EntryGenAt": "2025-05-29T20:32:00.0426109Z",
      "Similarity": 0.6160067214155055
    },
    {
      "Title": "Why Most Scrum Masters Are Failing and What They Should Know",
      "Slug": "why-most-scrum-masters-are-failing-and-what-they-should-know",
      "Reference": "resources/blog/2024/2024-09-05-the-incompetent-scrum-master-why-most-are-failing-and-what-they-should-know",
      "EntryId": "VTjU5Wl2XWU",
      "EntryKind": "resource",
      "EntryType": "blog",
      "EntryGenAt": "2025-05-29T20:34:29.2020232Z",
      "Similarity": 0.6079534210328852
    },
    {
      "Title": "Upskilled Engineering Teams",
      "Slug": "upskilled-engineering-teams",
      "Reference": "outcomes/upskilled-engineering-teams",
      "EntryId": "SepceedTcGN",
      "EntryKind": "marketing",
      "EntryType": "outcomes",
      "EntryGenAt": "2025-10-31T18:44:48.480691Z",
      "Similarity": 0.6010871581235504
    },
    {
      "Title": "Engineering can fix technical debt, but leadership has to invest in it",
      "Slug": "engineering-can-fix-technical-debt-but-leadership-has-to-invest-in-it",
      "Reference": "resources/signals/2025-03-03-engineering-can-fix-technical-debt-but-leadership-has-to-invest-in-it",
      "EntryId": "XRePaJiX1kj",
      "EntryKind": "resource",
      "EntryType": "signals",
      "EntryGenAt": "2025-05-29T20:32:05.9011591Z",
      "Similarity": 0.5930738863503687
    },
    {
      "Title": "There Is No Such Thing as a \"Junior\" Scrum Master",
      "Slug": "there-is-no-such-thing-as-a-junior-scrum-master",
      "Reference": "resources/blog/2025/2025-02-17-no-such-thing-as-a-junior-scrum-master",
      "EntryId": "f2RQh2UCwqB",
      "EntryKind": "resource",
      "EntryType": "blog",
      "EntryGenAt": "2025-05-29T20:32:35.9462022Z",
      "Similarity": 0.5924561411477515
    },
    {
      "Title": "Engineering Excellence in One Hour A Week",
      "Slug": "engineering-excellence-in-one-hour-a-week",
      "Reference": "capabilities/engineering-excellence-in-one-hour-a-week",
      "EntryId": "CwlqQrHDnTD",
      "EntryKind": "marketing",
      "EntryType": "capabilities",
      "EntryGenAt": "2025-10-31T18:44:34.8105532Z",
      "Similarity": 0.5890279290440749
    },
    {
      "Title": "Technical Leadership in One Hour A Week",
      "Slug": "technical-leadership-in-one-hour-a-week",
      "Reference": "capabilities/technical-leadership-in-one-hour-a-week",
      "EntryId": "U0akd22Voq8",
      "EntryKind": "marketing",
      "EntryType": "capabilities",
      "EntryGenAt": "2025-10-31T18:44:35.982255Z",
      "Similarity": 0.5845299202123204
    },
    {
      "Title": "Why Topic Branches Drive High-Quality Delivery",
      "Slug": "why-topic-branches-drive-high-quality-delivery",
      "Reference": "resources/blog/2025/2025-07-14-why-topic-branches-drive-high-quality-delivery",
      "EntryId": "O_VlmDj7n3V",
      "EntryKind": "resource",
      "EntryType": "blog",
      "EntryGenAt": "2025-05-29T20:30:07.5198747Z",
      "Similarity": 0.5812291406734845
    },
    {
      "Title": "Clarity in Technology Roadmaps",
      "Slug": "clarity-in-technology-roadmaps",
      "Reference": "outcomes/clarity-in-technology-roadmaps",
      "EntryId": "wTrT0eqFtmY",
      "EntryKind": "marketing",
      "EntryType": "outcomes",
      "EntryGenAt": "2025-10-31T18:44:55.7328099Z",
      "Similarity": 0.5342383226065059
    },
    {
      "Title": "Faster More Predictable Software Delivery",
      "Slug": "faster-more-predictable-software-delivery",
      "Reference": "outcomes/faster-more-predictable-software-delivery",
      "EntryId": "ew25L-Aydmr",
      "EntryKind": "marketing",
      "EntryType": "outcomes",
      "EntryGenAt": "2025-10-31T18:45:03.9011102Z",
      "Similarity": 0.5290477752919137
    },
    {
      "Title": "Investing for Business Agility - Using evidence-based portfolio management to achieve better business outcomes",
      "Slug": "investing-for-business-agility-using-evidence-based-portfolio-management-to-achieve-better-business-outcomes",
      "Reference": "resources/guides/evidence-based-portfolio-management",
      "EntryId": "KD08D48Weks",
      "EntryKind": "resource",
      "EntryType": "guides",
      "EntryGenAt": "2025-05-29T20:34:03.8865036Z",
      "Similarity": 0.5159916547730686
    },
    {
      "Title": "Manifesto for Agile Software Development",
      "Slug": "manifesto-for-agile-software-development",
      "Reference": "resources/guides/manifesto-for-agile-software-development",
      "EntryId": "poyC7fUGitC",
      "EntryKind": "resource",
      "EntryType": "guides",
      "EntryGenAt": "2025-05-29T20:34:13.6054486Z",
      "Similarity": 0.5088978162887686
    },
    {
      "Title": "Azure DevOps Migration Services",
      "Slug": "azure-devops-migration-services",
      "Reference": "capabilities/azure-devops-migration-services",
      "EntryId": "9VervIsddUa",
      "EntryKind": "marketing",
      "EntryType": "capabilities",
      "EntryGenAt": "2025-10-31T18:44:38.6691696Z",
      "Similarity": 0.5061691531102293
    },
    {
      "Title": "The Scrum Guide",
      "Slug": "the-scrum-guide",
      "Reference": "resources/guides/scrum-guide",
      "EntryId": "59gcHh1fYtC",
      "EntryKind": "resource",
      "EntryType": "guides",
      "EntryGenAt": "2025-05-29T20:34:07.6058577Z",
      "Similarity": 0.48948863272182075
    },
    {
      "Title": "Detecting Agile BS",
      "Slug": "detecting-agile-bs",
      "Reference": "resources/guides/detecting-agile-bs",
      "EntryId": "Tt8SPr3xJER",
      "EntryKind": "resource",
      "EntryType": "guides",
      "EntryGenAt": "2025-05-29T20:34:22.2965514Z",
      "Similarity": 0.4843547799098056
    },
    {
      "Title": "Azure DevOps/TFS to Github Migration Services",
      "Slug": "github-migration-services",
      "Reference": "capabilities/github-migration-services",
      "EntryId": "6NS_E7j1pRu",
      "EntryKind": "marketing",
      "EntryType": "capabilities",
      "EntryGenAt": "2025-10-31T18:44:37.2623034Z",
      "Similarity": 0.48114626977951047
    },
    {
      "Title": "AI Opportunity Discovery & Context Sourcing",
      "Slug": "ai-opportunity-discovery",
      "Reference": "capabilities/ai-opportunity-discovery",
      "EntryId": "p7M4Bv_h_Pa",
      "EntryKind": "marketing",
      "EntryType": "capabilities",
      "EntryGenAt": "2025-10-31T18:44:32.0528527Z",
      "Similarity": 0.46936477175831515
    },
    {
      "Title": "Nexus Guide",
      "Slug": "nexus-guide",
      "Reference": "resources/guides/nexus-framework",
      "EntryId": "iC8MlA3TE7S",
      "EntryKind": "resource",
      "EntryType": "guides",
      "EntryGenAt": "2025-05-29T20:34:05.7118225Z",
      "Similarity": 0.4619906011436159
    },
    {
      "Title": "Continuous Delivery Using Azure DevOps Services Training",
      "Slug": "continuous-delivery-using-azure-devops-services-training",
      "Reference": "capabilities/training-courses/accentient-continuous-delivery-using-azure-devops-services",
      "EntryId": "continuous-delivery-using-azure-devops-services-training",
      "EntryKind": "program",
      "EntryType": "course",
      "EntryGenAt": "2025-07-23T06:16:45.0305922Z",
      "Similarity": 0.45345469746549827
    },
    {
      "Title": "Applying Professional Scrum (APS) Course with Certification",
      "Slug": "applying-professional-scrum-aps-with-certification",
      "Reference": "capabilities/training-courses/scrumorg-applying-professional-scrum",
      "EntryId": "applying-professional-scrum-aps-with-certification",
      "EntryKind": "program",
      "EntryType": "course",
      "EntryGenAt": "2025-07-23T06:16:50.2672911Z",
      "Similarity": 0.4463639561338033
    },
    {
      "Title": "OKR Practitioner",
      "Slug": "okr-practitioner",
      "Reference": "capabilities/training-courses/okrmentors-okr-practitioners",
      "EntryId": "okr-practitioner",
      "EntryKind": "program",
      "EntryType": "course",
      "EntryGenAt": "2025-07-29T12:33:13.2064256Z",
      "Similarity": 0.4425801076957453
    },
    {
      "Title": "Applying Professional Kanban (APK) Course with Certification",
      "Slug": "applying-professional-kanban-apk-training-experience-with-certification",
      "Reference": "capabilities/training-courses/prokanban-applying-professional-kanban",
      "EntryId": "applying-professional-kanban-apk-training-experience-with-certification",
      "EntryKind": "program",
      "EntryType": "course",
      "EntryGenAt": "2025-07-23T06:16:36.1848201Z",
      "Similarity": 0.43459634243042083
    },
    {
      "Title": "Professional Scrum Product Owner (PSPO) Course with Certification",
      "Slug": "professional-scrum-product-owner-pspo-with-certification",
      "Reference": "capabilities/training-courses/scrumorg-professional-scrum-product-owner",
      "EntryId": "professional-scrum-product-owner-pspo-with-certification",
      "EntryKind": "program",
      "EntryType": "course",
      "EntryGenAt": "2025-07-23T06:16:42.4811201Z",
      "Similarity": 0.43012678424379314
    }
  ],
  "target": {
    "EntryKind": "classification",
    "Title": "Technical Mastery",
    "Reference": "tags/technical-mastery",
    "EntryId": "yRJScYUkBmu",
    "GeneratedAt": "2025-11-05T01:14:03.1535082-05:00",
    "Slug": null,
    "EntryType": "tags"
  }
}
